extract_tex_env/__init__.py
extract_tex_env/__main__.py
extract_tex_env/functions_tex.py
extract_tex_env/main.py
extract_tex_env-0.1.1.dist-info/METADATA
extract_tex_env-0.1.1.dist-info/WHEEL
extract_tex_env-0.1.1.dist-info/entry_points.txt
extract_tex_env-0.1.1.dist-info/RECORD
