Metadata-Version: 2.1
Name: extract-tex-env
Version: 0.1.1
Summary: Turned on to show default values.
Author: vaibhavblayer
Author-email: vaibhavblayer@gmail.com
Requires-Python: >=3.11,<4.0
Classifier: Programming Language :: Python :: 3
Classifier: Programming Language :: Python :: 3.11
